byebyebots/byebyebots.py
byebyebots/version.py
byebyebots-0.1.0.dist-info/LICENSE
byebyebots-0.1.0.dist-info/METADATA
byebyebots-0.1.0.dist-info/WHEEL
byebyebots-0.1.0.dist-info/entry_points.txt
byebyebots-0.1.0.dist-info/top_level.txt
byebyebots-0.1.0.dist-info/RECORD
