Metadata-Version: 2.1
Name: byebyebots
Version: 0.1.0
Summary: Unsubscribe bot-like users from the Instagram account
Home-page: https://github.com/VikGit/byebyebots-instagram.git
Author: Viktor Krasheninnikov
Author-email: krasherspost@gmail.com
License: MIT License
Requires-Dist: InstagramApi (==1.0.2)
Requires-Dist: bs4 (==0.0.1)
